{
    "Exotic": "异域",
    "Hunter": "猎人",
    "Titan": "泰坦",
    "Warlock": "术士",
    "Super": "超能",
    "Helmet": "头盔",
    "Mobility": "韧性",
    "Resilience": "强度",
    "Recovery": "恢复",
    "Discipline": "戒律",
    "Intellect": "智力",
    "Strength": "力量",
    "Grenade": "手雷",
    "Melee": "近战",
    "Gauntlets": "臂铠",
    "Chest Armor": "胸甲",
    "Leg Armor": "腿甲",
    "Nerf": "削弱",
    "Class Item": "职业物品",
    "Perk": "特性",
    "Perks": "特性",
    "Swords": "剑",
    "Bows": "弓箭",
    "Glaives": "偃月",
    "Sidearms": "手枪",
    "Shotgun": "霰弹枪",
    "Shotguns": "霰弹枪",
    "SMGs": "微型冲锋枪",
    "Machine Guns": "机枪",
    "Hand Cannons": "手炮",
    "Auto Rifles":"自动步枪",
    "Scout Rifles":"斥候步枪",
    "Pulse Rifles": "脉冲步枪",
    "Trace Rifles": "追踪步枪",
    "Fusion Rifle": "融合步枪",
    "Fusion Rifles": "融合步枪",
    "Sniper Rifle": "狙击步枪",
    "Sniper Rifles": "狙击步枪",
    "Rocket Launchers": "火箭筒",
    "Grenade Launchers": "榴弹发射器",
    "Linear Fusion Rifle": "线性融合步枪",
    "Linear Fusion Rifles": "线性融合步枪",
    "Heavy Grenade Launchers": "重型榴弹发射器",
    "Special Grenade Launchers": "特种榴弹发射器",
    "Catalyst": "催化",
    "Nightfall": "日落",
    "The Vanguard": "先锋",
    "Vanguard": "先锋",
    "Gambit": "智谋",
    "Crucible": "熔炉",
    "Aim Assistance": "辅助瞄准",
    "Armor Charge": "护甲充能",
    "Finisher": "终结技",
    "Dungeon": "地牢",
    "Strike": "打击",
    "Patrol": "巡逻",
    "Public Event": "公开活动",
    "Lost Sector": "遗失区域",
    "Seasonal Activity": "赛季活动",
    "Kinetic": "动能",
    "Stasis": "冰影",
    "Strand": "缚丝",
    "Season": "赛季",
    "Engram": "记忆水晶",
    "Bounty": "悬赏",
    "Artifact": "神器",
    "Shader": "着色器",
    "Arc": "电弧",
    "Solar": "烈日",
    "Void": "虚空",
    "Collections": "收藏品",
    "Vendor": "商人",
    "Faction": "阵营",
    "Eververse": "永恒之诗",
    "Season Pass": "赛季通行证",
    "Bright Dust": "光尘",
    "Legendary Shards": "传说碎片",
    "Enhancement Cores": "强化核心",
    "Enhancement Prisms": "强化棱镜",
    "Ascendant Shards": "升华碎片",
    "Ascendant Alloy": "升华合金",
    "Glimmer": "微光币",
    "Champion": "勇士",
    "Barrier Champion": "屏障勇士",
    "Overload Champion": "过载勇士",
    "Unstoppable Champion": "不屈勇士",
    "Anti-Champion": "反勇士",
    "Artifact Perks": "神器模组",
    "Exotic Armor": "异域护甲",
    "Exotic Weapon": "异域武器",
    "Legendary Armor": "传说护甲",
    "Legendary Weapon": "传说武器",
    "Masterwork": "大师杰作"
}
